tnfsh_timetable_core/__init__.py
tnfsh_timetable_core/abc/__init__.py
tnfsh_timetable_core/abc/cache_abc.py
tnfsh_timetable_core/abc/crawler_abc.py
tnfsh_timetable_core/abc/domain_abc.py
tnfsh_timetable_core/index/__init__.py
tnfsh_timetable_core/index/cache.py
tnfsh_timetable_core/index/crawler.py
tnfsh_timetable_core/index/index.py
tnfsh_timetable_core/index/models.py
tnfsh_timetable_core/scheduling/__init__.py
tnfsh_timetable_core/scheduling/models.py
tnfsh_timetable_core/scheduling/rotation.py
tnfsh_timetable_core/scheduling/scheduling.py
tnfsh_timetable_core/scheduling/swap.py
tnfsh_timetable_core/scheduling/utils.py
tnfsh_timetable_core/timetable/__init__.py
tnfsh_timetable_core/timetable/cache.py
tnfsh_timetable_core/timetable/crawler.py
tnfsh_timetable_core/timetable/models.py
tnfsh_timetable_core/timetable_slot_log_dict/__init__.py
tnfsh_timetable_core/timetable_slot_log_dict/cache.py
tnfsh_timetable_core/timetable_slot_log_dict/crawler.py
tnfsh_timetable_core/timetable_slot_log_dict/models.py
tnfsh_timetable_core/timetable_slot_log_dict/timetable_slot_log_dict.py
tnfsh_timetable_core/utils/__init__.py
tnfsh_timetable_core/utils/dict_like.py
tnfsh_timetable_core/utils/logger.py
tnfsh_timetable_core-0.0.9.dist-info/licenses/LICENSE
tnfsh_timetable_core-0.0.9.dist-info/METADATA
tnfsh_timetable_core-0.0.9.dist-info/WHEEL
tnfsh_timetable_core-0.0.9.dist-info/top_level.txt
tnfsh_timetable_core-0.0.9.dist-info/RECORD
