Metadata-Version: 2.4
Name: tnfsh-timetable-core
Version: 0.0.9
Summary: 台南一中課表核心功能庫
Author-email: Skywind5487 <skywind5487@gmail.com>
License-Expression: MIT
Project-URL: Source, https://github.com/skywind5487/tnfsh-timetable-core
Keywords: timetable,scheduling,education
Classifier: Development Status :: 3 - Alpha
Classifier: Intended Audience :: Education
Classifier: Programming Language :: Python :: 3
Classifier: Programming Language :: Python :: 3.8
Classifier: Programming Language :: Python :: 3.9
Classifier: Programming Language :: Python :: 3.10
Classifier: Programming Language :: Python :: 3.11
Classifier: Programming Language :: Python :: 3.12
Requires-Python: >=3.8
License-File: LICENSE
Requires-Dist: aiohttp>=3.8.0
Requires-Dist: async>=0.6.2
Requires-Dist: beautifulsoup4>=4.9.3
Requires-Dist: bs4>=0.0.2
Requires-Dist: dotenv>=0.9.9
Requires-Dist: pydantic>=2.0.0
Requires-Dist: pytest>=8.3.5
Requires-Dist: pytest-asyncio>=0.24.0
Requires-Dist: requests>=2.32.3
Provides-Extra: dev
Requires-Dist: pytest>=6.0.0; extra == "dev"
Requires-Dist: pytest-asyncio>=0.14.0; extra == "dev"
Requires-Dist: black>=22.0.0; extra == "dev"
Requires-Dist: isort>=5.0.0; extra == "dev"
Requires-Dist: mypy>=0.900; extra == "dev"
Requires-Dist: build>=1.2.2.post1; extra == "dev"
Requires-Dist: pytest>=8.3.5; extra == "dev"
Requires-Dist: pytest-asyncio>=0.24.0; extra == "dev"
Dynamic: license-file
